setup.py
BlockmanROpI/BlockmanROpI.py
BlockmanROpI/__init__.py
BlockmanROpI.egg-info/PKG-INFO
BlockmanROpI.egg-info/SOURCES.txt
BlockmanROpI.egg-info/dependency_links.txt
BlockmanROpI.egg-info/top_level.txt