Metadata-Version: 1.0
Name: BlockmanROpI
Version: 0.0.1
Summary: calculates cumulative investment and ROI
Home-page: UNKNOWN
Author: UNKNOWN
Author-email: UNKNOWN
License: UNKNOWN
Platform: UNKNOWN
